Shikhandi/__init__.py
Shikhandi/main.py
Shikhandi/renren.py
Shikhandi-0.1.0.dist-info/DESCRIPTION.rst
Shikhandi-0.1.0.dist-info/METADATA
Shikhandi-0.1.0.dist-info/RECORD
Shikhandi-0.1.0.dist-info/WHEEL
Shikhandi-0.1.0.dist-info/metadata.json
Shikhandi-0.1.0.dist-info/top_level.txt
