Metadata-Version: 2.0
Name: Shikhandi
Version: 0.1.0
Summary: A backup tool for renren. You can backup any of your friends' timeline and photos to local with it.
Home-page: https://github.com/WillSkywalker/Shikhandi
Author: Will Skywalker
Author-email: cxbats@gmail.com
License: Apache 2.0
Keywords: crawler renren
Platform: UNKNOWN
Classifier: Development Status :: 2 - Pre-Alpha
Classifier: Intended Audience :: Developers
Classifier: Topic :: Software Development :: Libraries :: Python Modules
Classifier: License :: OSI Approved :: Apache Software License
Classifier: Programming Language :: Python :: 3
Classifier: Programming Language :: Python :: 3.2
Classifier: Programming Language :: Python :: 3.3
Classifier: Programming Language :: Python :: 3.4
Requires-Dist: beautifulsoup4 (==4.5.1)
Requires-Dist: bs4 (==0.0.1)
Requires-Dist: requests (==2.11.1)
